{
  "author": "Microsoft",
  "name": "Progetto di test di .NET Aspire (NUnit)",
  "description": "Un progetto che contiene test di integrazione NUnit di un progetto app host di .NET Aspire.",
  "symbols/Framework/description": "Il framework di destinazione per il progetto.",
  "symbols/Framework/choices/net8.0/description": "Destinazione net8.0",
  "symbols/Framework/choices/net9.0/description": "Net9.0 di destinazione",
  "symbols/AspireVersionCli/description": "La versione di .NET Aspire da usare.",
  "symbols/AspireVersionCli/displayName": "Versione di .NET Aspire",
  "symbols/AspireVersionCli/choices/9.1/displayName": "9.1",
  "symbols/AspireVersionCli/choices/9.1/description": "Sceglie .NET Aspire 9.1",
  "symbols/AspireVersionCli/choices/9.0/displayName": "9.0",
  "symbols/AspireVersionCli/choices/9.0/description": "Sceglie .NET Aspire 9.0",
  "symbols/AspireVersionCli/choices/8.2/displayName": "8.2",
  "symbols/AspireVersionCli/choices/8.2/description": "Sceglie .NET Aspire 8.2 (valido solo quando è specificato '--framework net8.0')",
  "symbols/AspireVersion/description": "Versione di .NET Aspire da usare.",
  "symbols/AspireVersion/displayName": "Versione di .NET Aspire",
  "symbols/AspireVersion/choices/9.1/displayName": "9.1",
  "symbols/AspireVersion/choices/9.1/description": "Sceglie .NET Aspire 9.1",
  "symbols/AspireVersion/choices/9.0/displayName": "9.0",
  "symbols/AspireVersion/choices/9.0/description": "Sceglie .NET Aspire 9.0",
  "symbols/AspireVersion/choices/8.2/displayName": "8.2",
  "symbols/AspireVersion/choices/8.2/description": "Sceglie .NET Aspire 8.2",
  "symbols/AspireVersionNet9/description": "La versione di .NET Aspire da usare.",
  "symbols/AspireVersionNet9/displayName": "Versione di .NET Aspire",
  "symbols/AspireVersionNet9/choices/9.1/displayName": "9.1",
  "symbols/AspireVersionNet9/choices/9.1/description": "Sceglie .NET Aspire 9.1",
  "symbols/AspireVersionNet9/choices/9.0/displayName": "9.0",
  "symbols/AspireVersionNet9/choices/9.0/description": "Sceglie .NET Aspire 9.0",
  "symbols/skipRestore/description": "Se specificato, ignora il ripristino automatico del progetto durante la creazione.",
  "postActions/restore/description": "Ripristina i pacchetti NuGet richiesti da questo progetto.",
  "postActions/restore/manualInstructions/default/text": "Esegui 'dotnet restore'"
}